[["Map",1,2,7,8],"meta::meta",["Map",3,4,5,6],"astro-version","5.13.0","astro-config-digest","{\"root\":{},\"srcDir\":{},\"publicDir\":{},\"outDir\":{},\"cacheDir\":{},\"site\":\"https://example.com\",\"compressHTML\":true,\"base\":\"/\",\"trailingSlash\":\"ignore\",\"output\":\"static\",\"scopedStyleStrategy\":\"attribute\",\"build\":{\"format\":\"directory\",\"client\":{},\"server\":{},\"assets\":\"_astro\",\"serverEntry\":\"entry.mjs\",\"redirects\":true,\"inlineStylesheets\":\"auto\",\"concurrency\":1},\"server\":{\"open\":false,\"host\":false,\"port\":4321,\"streaming\":true,\"allowedHosts\":[]},\"redirects\":{},\"image\":{\"endpoint\":{\"route\":\"/_image\"},\"service\":{\"entrypoint\":\"astro/assets/services/sharp\",\"config\":{}},\"domains\":[],\"remotePatterns\":[],\"responsiveStyles\":false},\"devToolbar\":{\"enabled\":true},\"markdown\":{\"syntaxHighlight\":{\"type\":\"shiki\",\"excludeLangs\":[\"math\"]},\"shikiConfig\":{\"langs\":[],\"langAlias\":{},\"theme\":\"github-dark\",\"themes\":{},\"wrap\":false,\"transformers\":[]},\"remarkPlugins\":[],\"rehypePlugins\":[],\"remarkRehype\":{},\"gfm\":true,\"smartypants\":true},\"security\":{\"checkOrigin\":true},\"env\":{\"schema\":{},\"validateSecrets\":false},\"experimental\":{\"clientPrerender\":false,\"contentIntellisense\":false,\"headingIdCompat\":false,\"preserveScriptOrder\":false,\"liveContentCollections\":false,\"csp\":false,\"staticImportMetaEnv\":false,\"chromeDevtoolsWorkspace\":false},\"legacy\":{\"collections\":false}}","products",["Map",9,10,24,25],"herbal-supplement",{"id":9,"data":11,"body":19,"filePath":20,"digest":21,"legacyId":22,"deferredRender":23},{"title":12,"description":13,"subtitle":14,"price":15,"price_old":16,"image":17,"short":18,"slug":9},"Herbal Supplement","First product","Daily health support","25 €","30 €","../../assets/product1.png","Herbal supplement for daily wellness.","Content for product 1.\r\nDetails about herbal supplement.","src/content/products/product-1.mdx","1c98dc906c345c5f","product-1.mdx",true,"natural-cream",{"id":24,"data":26,"body":33,"filePath":34,"digest":35,"legacyId":36,"deferredRender":23},{"title":27,"description":28,"subtitle":29,"price":30,"image":31,"short":32,"slug":24},"Natural Cream","Second product","Soothing skin care","18 €","../../assets/product2.png","Natural cream that soothes and nourishes.","Content for product 2.\r\nDetails about natural cream.","src/content/products/product-2.mdx","f78e6e5b1f80217a","product-2.mdx"]